setup.py
pod_picker/__init__.py
pod_picker/pod_model.py
pod_picker/pod_picker.py
pod_picker.egg-info/PKG-INFO
pod_picker.egg-info/SOURCES.txt
pod_picker.egg-info/dependency_links.txt
pod_picker.egg-info/entry_points.txt
pod_picker.egg-info/requires.txt
pod_picker.egg-info/top_level.txt
test/test_command.py